steam_troy/__init__.py
steam_troy/exceptions.py
steam_troy/game_servers.py
steam_troy/globalid.py
steam_troy/guard.py
steam_troy/steamid.py
steam_troy/webapi.py
steam_troy/webauth.py
steam_troy/client/__init__.py
steam_troy/client/cdn.py
steam_troy/client/gc.py
steam_troy/client/user.py
steam_troy/core/__init__.py
steam_troy/core/cm.py
steam_troy/core/connection.py
steam_troy/core/crypto.py
steam_troy/core/manifest.py
steam_troy/enums/__init__.py
steam_troy/enums/base.py
steam_troy/enums/common.py
steam_troy/enums/emsg.py
steam_troy/protobufs/__init__.py
steam_troy/protobufs/content_manifest_pb2.py
steam_troy/protobufs/encrypted_app_ticket_pb2.py
steam_troy/protobufs/gc_pb2.py
steam_troy/protobufs/steammessages_base_pb2.py
steam_troy/protobufs/steammessages_broadcast_pb2.py
steam_troy/protobufs/steammessages_chat_pb2.py
steam_troy/protobufs/steammessages_clientserver_2_pb2.py
steam_troy/protobufs/steammessages_clientserver_friends_pb2.py
steam_troy/protobufs/steammessages_clientserver_login_pb2.py
steam_troy/protobufs/steammessages_clientserver_pb2.py
steam_troy/protobufs/steammessages_cloud_pb2.py
steam_troy/protobufs/steammessages_credentials_pb2.py
steam_troy/protobufs/steammessages_datapublisher_pb2.py
steam_troy/protobufs/steammessages_depotbuilder_pb2.py
steam_troy/protobufs/steammessages_deviceauth_pb2.py
steam_troy/protobufs/steammessages_econ_pb2.py
steam_troy/protobufs/steammessages_friendmessages_pb2.py
steam_troy/protobufs/steammessages_gamenotifications_pb2.py
steam_troy/protobufs/steammessages_gameservers_pb2.py
steam_troy/protobufs/steammessages_inventory_pb2.py
steam_troy/protobufs/steammessages_linkfilter_pb2.py
steam_troy/protobufs/steammessages_offline_pb2.py
steam_troy/protobufs/steammessages_parental_pb2.py
steam_troy/protobufs/steammessages_partnerapps_pb2.py
steam_troy/protobufs/steammessages_physicalgoods_pb2.py
steam_troy/protobufs/steammessages_player_pb2.py
steam_troy/protobufs/steammessages_publishedfile_pb2.py
steam_troy-0.9.2.dist-info/LICENSE
steam_troy-0.9.2.dist-info/METADATA
steam_troy-0.9.2.dist-info/WHEEL
steam_troy-0.9.2.dist-info/top_level.txt
steam_troy-0.9.2.dist-info/zip-safe
steam_troy-0.9.2.dist-info/RECORD
