Metadata-Version: 2.1
Name: steam-troy
Version: 0.9.2
Summary: Module for interacting with various Steam features
Home-page: https://github.com/ValvePython/steam
Author: Rossen Georgiev
Author-email: rossen@rgp.io
License: MIT
Keywords: valve steam steamid api webapi steamcommunity
Platform: UNKNOWN
Classifier: Development Status :: 5 - Production/Stable
Classifier: Natural Language :: English
Classifier: Intended Audience :: Developers
Classifier: License :: OSI Approved :: MIT License
Classifier: Operating System :: OS Independent
Classifier: Programming Language :: Python :: 2.7
Classifier: Programming Language :: Python :: 3.4
Classifier: Programming Language :: Python :: 3.5
Classifier: Programming Language :: Python :: 3.6
Classifier: Programming Language :: Python :: Implementation :: PyPy
Requires-Dist: six (>=1.10)
Requires-Dist: pycryptodomex (>=3.7.0)
Requires-Dist: requests (<2.22.0,>=2.9.1)
Requires-Dist: vdf (>=2.0)
Requires-Dist: gevent (>=1.2.0)
Requires-Dist: protobuf (>=3.0.0)
Requires-Dist: gevent-eventemitter (>=2.1)
Requires-Dist: cachetools (>=3.0.0)
Provides-Extra: client
